Metadata-Version: 2.1
Name: CPVI
Version: 0.1.4b0
Summary: Comprehensive Persian Verb Inflector
Home-page: https://github.com/asdoost/CPVI
Author: Abbas Safardoost
Author-email: a.safardoust@gmail.com
License: MIT
Download-URL: https://github.com/asdoost/CPVI/archive/refs/tags/v0.1.4-beta.tar.gz
Platform: UNKNOWN
Classifier: Topic :: Text Processing
Classifier: License :: OSI Approved :: MIT License
Classifier: Natural Language :: Persian
Classifier: Programming Language :: Python :: 3.6
Classifier: Programming Language :: Python :: 3.7
Classifier: Programming Language :: Python :: 3.8
Classifier: Programming Language :: Python :: 3.9
License-File: LICENSE.txt
